<?xml version="1.0" encoding="UTF-8"?>
<entity-mappings xmlns="http://xmlns.jcp.org/xml/ns/persistence/orm"
                 xmlns:xsi="http://www.w3.org/2001/XMLSchema-instance"
                 xsi:schemaLocation="http://xmlns.jcp.org/xml/ns/persistence/orm
                                     http://xmlns.jcp.org/xml/ns/persistence/orm_2_2.xsd"
                 version="2.2">

    <entity class="models.Movie" name="Movie">
        <table name="Movie"/>
        <attributes>
            <id name="id">
                <generated-value strategy="IDENTITY"/>
            </id>
            <basic name="title">
                <column name="title"/>
            </basic>
            <basic name="dateOfRelease">
                <column name="date_of_release"/>
            </basic>
            <basic name="duration">
                <column name="duration"/>
            </basic>
            <basic name="boxOffice">
                <column name="box_office"/>
            </basic>
            <many-to-one name="filmCompany" target-entity="models.FilmCompany" fetch="EAGER">
                <join-column name="film_company_id" referenced-column-name="id"/>
            </many-to-one>
            <many-to-many name="actors" target-entity="models.Actor">
                <join-table name="Actor_Movie">
                    <join-column name="movie_id" referenced-column-name="id"/>
                    <inverse-join-column name="actor_id" referenced-column-name="id"/>
                </join-table>
                <cascade>
                    <cascade-all/>
                </cascade>
            </many-to-many>
            <many-to-many name="genres" target-entity="models.Genre">
                <join-table name="genre_movie">
                    <join-column name="movie_id" referenced-column-name="id"/>
                    <inverse-join-column name="genre_id" referenced-column-name="id"/>
                </join-table>
                <cascade>
                    <cascade-all/>
                </cascade>
            </many-to-many>
        </attributes>
    </entity>

</entity-mappings>
